sancty/__init__.py
sancty/cli.py
sancty/deps_types.py
sancty/main.py
sancty/patch_blessed/__init__.py
sancty/patch_blessed/terminal.py
sancty/read.py
sancty/render.py
sancty/run.py
sancty-0.2.1.dist-info/entry_points.txt
sancty-0.2.1.dist-info/LICENSE
sancty-0.2.1.dist-info/WHEEL
sancty-0.2.1.dist-info/METADATA
sancty-0.2.1.dist-info/RECORD
