Metadata-Version: 2.1
Name: sancty
Version: 0.2.1
Summary: Sancty is an extension to jquast/blessed for simple editor-like terminal apps
License: Apache-2.0
Author: Tip ten Brink
Author-email: 75669206+tiptenbrink@users.noreply.github.com
Requires-Python: >=3.10,<4.0
Classifier: License :: OSI Approved :: Apache Software License
Classifier: Programming Language :: Python :: 3
Classifier: Programming Language :: Python :: 3.10
Requires-Dist: blessed (==1.19.0)
Requires-Dist: cwcwidth (>=0.1.5,<0.2.0)
Project-URL: Source Code, https://github.com/tiptenbrink/sancty
